can_filler/can_filler.py
can_filler/serial_rx_tx.py
can_filler-0.1.dist-info/METADATA
can_filler-0.1.dist-info/WHEEL
can_filler-0.1.dist-info/top_level.txt
can_filler-0.1.dist-info/RECORD
