Metadata-Version: 2.1
Name: can-filler
Version: 0.1
Summary: Beer Can Filler Program
Home-page: https://github.com/senoird/can_filler
Author: Moore Brewing
Author-email: senoird@gmail.com
License: MIT
Platform: UNKNOWN
